pynthlib/__init__.py
pynthlib/eval.py
pynthlib/pynth.py
pynthlib-0.0.3.dist-info/LICENSE.txt
pynthlib-0.0.3.dist-info/METADATA
pynthlib-0.0.3.dist-info/WHEEL
pynthlib-0.0.3.dist-info/top_level.txt
pynthlib-0.0.3.dist-info/RECORD
