Metadata-Version: 2.1
Name: pynthlib
Version: 0.0.3
Summary: Intuitive sound synthesis in python.
Home-page: https://github.com/MatejBevec/pynth
Author: Matej Bevec
Author-email: matejbevec98@gmail.com
License: MIT
Project-URL: repository, https://github.com/MatejBevec/pynth
Classifier: Development Status :: 1 - Planning
Classifier: Programming Language :: Python :: 3
Classifier: Operating System :: Microsoft :: Windows
Classifier: Operating System :: MacOS :: MacOS X
Classifier: Operating System :: Unix
Classifier: Operating System :: POSIX
Requires-Python: >=3.8
License-File: LICENSE.txt
Requires-Dist: keyboard (>=0.13)
Requires-Dist: numpy (>=1.21.0)
Requires-Dist: scipy (>=1.7.0)
Requires-Dist: sounddevice (>=0.4.2)
Requires-Dist: matplotlib (>=3.2.0)
Requires-Dist: graphviz (>=0.14)
